{"provider": "MOUNT AUBURN HOSPITAL", "person": {"prefix": "Mr.", "name": "Keith Beahan", "birthday": "1917-04-07", "gender": "male", "address": "Suite 746,432 Dereck Lock,Cambridge,US", "phone": [{"system": "phone", "value": "1-745-862-0000", "use": "home"}], "languages": ["en-US"]}, "conds": [{"date": "1935-12-05", "type": "Hypertension", "status": "active"}, {"date": "1965-01-14", "type": "Chronic sinusitis (disorder)", "status": "active"}, {"date": "1968-10-29", "type": "Suspected lung cancer (situation)", "status": "active"}, {"date": "1968-11-11", "type": "Non-small cell lung cancer (disorder)", "status": "active"}, {"date": "1968-11-12", "type": "Non-small cell carcinoma of lung, TNM stage 4 (disorder)", "status": "active"}], "immuns": [], "medreqs": [{"type": "Penicillin V Potassium 250 MG", "code": "834060", "date": "1918-04-17", "status": "active", "dosage": ""}], "observs": {"Cause of Death [US Standard Certificate of Death]": {"units": "N/A", "values": [{"date": "1969-05-23", "value": "Non-small cell lung cancer (disorder)"}]}, "Quality adjusted life years": {"units": "years", "values": [{"date": "2017-10-31", "value": 51.442719981627114}]}, "Disability rating scale": {"units": "years", "values": [{"date": "2017-10-31", "value": 36.34176001837288}]}}}