{"provider": "ST VINCENT HOSPITAL WOMEN'S CENTER", "person": {"prefix": "Mrs.", "name": "Glynda Beahan", "birthday": "1971-04-02", "gender": "female", "address": "93389 Schamberger Gardens,Millbury,US", "phone": [{"system": "phone", "value": "997.490.4231 x976", "use": "home"}], "languages": ["en-US"]}, "conds": [{"date": "2008-12-21", "type": "Acute bacterial sinusitis (disorder)", "status": "resolved"}], "immuns": [{"date": "2009-07-05T08:14:27-04:00", "type": "Influenza, seasonal, injectable, preservative free"}, {"date": "2012-08-14T18:04:52-04:00", "type": "Influenza, seasonal, injectable, preservative free"}, {"date": "2012-08-14T18:04:52-04:00", "type": "Td (adult) preservative free"}, {"date": "2014-11-06T01:48:07-05:00", "type": "Influenza, seasonal, injectable, preservative free"}, {"date": "2016-07-06T14:32:59-04:00", "type": "Influenza, seasonal, injectable, preservative free"}], "medreqs": [], "observs": {"Body Height": {"units": "cm", "values": [{"date": "2009-07-05", "value": 157.9030880758585}, {"date": "2012-08-14", "value": 157.9030880758585}, {"date": "2014-11-06", "value": 157.9030880758585}, {"date": "2016-07-06", "value": 157.9030880758585}]}, "Body Weight": {"units": "kg", "values": [{"date": "2009-07-05", "value": 87.3618428446033}, {"date": "2012-08-14", "value": 92.06313576272585}, {"date": "2014-11-06", "value": 94.74976117273611}, {"date": "2016-07-06", "value": 97.88245270322865}]}, "Body Mass Index": {"units": "kg/m2", "values": [{"date": "2009-07-05", "value": 35.03809934356171}, {"date": "2012-08-14", "value": 36.923640707442594}, {"date": "2014-11-06", "value": 38.00116202509978}, {"date": "2016-07-06", "value": 39.2575864946863}]}, "Systolic Blood Pressure": {"units": "mmHg", "values": [{"date": "2009-07-05", "value": 136}, {"date": "2012-08-14", "value": 102}, {"date": "2014-11-06", "value": 120}, {"date": "2016-07-06", "value": 112}]}, "Diastolic Blood Pressure": {"units": "mmHg", "values": [{"date": "2009-07-05", "value": 84}, {"date": "2012-08-14", "value": 77}, {"date": "2014-11-06", "value": 71}, {"date": "2016-07-06", "value": 86}]}, "Total Cholesterol": {"units": "mg/dL", "values": [{"date": "2009-07-05", "value": 195}, {"date": "2012-08-14", "value": 193}, {"date": "2016-07-06", "value": 179}]}, "Triglycerides": {"units": "mg/dL", "values": [{"date": "2009-07-05", "value": 138}, {"date": "2012-08-14", "value": 115}, {"date": "2016-07-06", "value": 119}]}, "Low Density Lipoprotein Cholesterol": {"units": "mg/dL", "values": [{"date": "2009-07-05", "value": 90}, {"date": "2012-08-14", "value": 109}, {"date": "2016-07-06", "value": 84}]}, "High Density Lipoprotein Cholesterol": {"units": "mg/dL", "values": [{"date": "2009-07-05", "value": 77}, {"date": "2012-08-14", "value": 61}, {"date": "2016-07-06", "value": 71}]}, "Quality adjusted life years": {"units": "years", "values": [{"date": "2017-10-31", "value": 45.988378692538504}]}, "Disability rating scale": {"units": "years", "values": [{"date": "2017-10-31", "value": 0.011621307461495516}]}}}