{"provider": "SPAULDING AQUATICS PRGRM - YARMOUTH", "person": {"prefix": "Mr.", "name": "Bernard Parker", "birthday": "1960-12-28", "gender": "male", "address": "7739 Heller Harbor,Yarmouth,US", "phone": [{"system": "phone", "value": "906-964-0683 x81058", "use": "home"}], "languages": ["es"]}, "conds": [{"date": "2011-07-08", "type": "Acute bronchitis (disorder)", "status": "resolved"}], "immuns": [{"date": "2009-05-24T06:25:30-04:00", "type": "Influenza, seasonal, injectable, preservative free"}, {"date": "2011-05-25T18:05:03-04:00", "type": "Influenza, seasonal, injectable, preservative free"}, {"date": "2012-06-01T18:37:41-04:00", "type": "Influenza, seasonal, injectable, preservative free"}, {"date": "2012-06-01T18:37:41-04:00", "type": "Td (adult) preservative free"}, {"date": "2013-06-23T19:48:25-04:00", "type": "Influenza, seasonal, injectable, preservative free"}, {"date": "2014-07-08T03:07:59-04:00", "type": "Influenza, seasonal, injectable, preservative free"}, {"date": "2015-07-09T12:18:58-04:00", "type": "Influenza, seasonal, injectable, preservative free"}, {"date": "2016-06-21T03:09:34-04:00", "type": "Influenza, seasonal, injectable, preservative free"}, {"date": "2017-07-14T02:23:43-04:00", "type": "Influenza, seasonal, injectable, preservative free"}], "medreqs": [{"type": "Acetaminophen 160 MG", "code": "608680", "date": "2011-07-11", "status": "stopped", "dosage": ""}], "observs": {"Body Height": {"units": "cm", "values": [{"date": "2009-05-24", "value": 181.5156504725856}, {"date": "2011-05-25", "value": 181.5156504725856}, {"date": "2012-06-01", "value": 181.5156504725856}, {"date": "2013-06-23", "value": 181.5156504725856}, {"date": "2014-07-08", "value": 181.5156504725856}, {"date": "2015-07-09", "value": 181.5156504725856}, {"date": "2016-06-21", "value": 181.5156504725856}, {"date": "2017-07-14", "value": 181.5156504725856}]}, "Body Weight": {"units": "kg", "values": [{"date": "2009-05-24", "value": 120.08267191091039}, {"date": "2011-05-25", "value": 121.65090737411326}, {"date": "2012-06-01", "value": 121.65090737411326}, {"date": "2013-06-23", "value": 121.65090737411326}, {"date": "2014-07-08", "value": 121.65090737411326}, {"date": "2015-07-09", "value": 121.65090737411326}, {"date": "2016-06-21", "value": 121.65090737411326}, {"date": "2017-07-14", "value": 121.65090737411326}]}, "Body Mass Index": {"units": "kg/m2", "values": [{"date": "2009-05-24", "value": 36.44619462606283}, {"date": "2011-05-25", "value": 36.92216850307474}, {"date": "2012-06-01", "value": 36.92216850307474}, {"date": "2013-06-23", "value": 36.92216850307474}, {"date": "2014-07-08", "value": 36.92216850307474}, {"date": "2015-07-09", "value": 36.92216850307474}, {"date": "2016-06-21", "value": 36.92216850307474}, {"date": "2017-07-14", "value": 36.92216850307474}]}, "Systolic Blood Pressure": {"units": "mmHg", "values": [{"date": "2009-05-24", "value": 102}, {"date": "2011-05-25", "value": 111}, {"date": "2012-06-01", "value": 131}, {"date": "2013-06-23", "value": 101}, {"date": "2014-07-08", "value": 124}, {"date": "2015-07-09", "value": 104}, {"date": "2016-06-21", "value": 115}, {"date": "2017-07-14", "value": 110}]}, "Diastolic Blood Pressure": {"units": "mmHg", "values": [{"date": "2009-05-24", "value": 89}, {"date": "2011-05-25", "value": 79}, {"date": "2012-06-01", "value": 82}, {"date": "2013-06-23", "value": 83}, {"date": "2014-07-08", "value": 75}, {"date": "2015-07-09", "value": 87}, {"date": "2016-06-21", "value": 86}, {"date": "2017-07-14", "value": 81}]}, "Total Cholesterol": {"units": "mg/dL", "values": [{"date": "2011-05-25", "value": 164}, {"date": "2014-07-08", "value": 195}, {"date": "2017-07-14", "value": 166}]}, "Triglycerides": {"units": "mg/dL", "values": [{"date": "2011-05-25", "value": 132}, {"date": "2014-07-08", "value": 102}, {"date": "2017-07-14", "value": 125}]}, "Low Density Lipoprotein Cholesterol": {"units": "mg/dL", "values": [{"date": "2011-05-25", "value": 62}, {"date": "2014-07-08", "value": 95}, {"date": "2017-07-14", "value": 82}]}, "High Density Lipoprotein Cholesterol": {"units": "mg/dL", "values": [{"date": "2011-05-25", "value": 75}, {"date": "2014-07-08", "value": 79}, {"date": "2017-07-14", "value": 59}]}, "Quality adjusted life years": {"units": "years", "values": [{"date": "2017-10-31", "value": 55.96043684151913}]}, "Disability rating scale": {"units": "years", "values": [{"date": "2017-10-31", "value": 0.03956315848087008}]}}}