{"provider": "FAIRVIEW HOSP MEDICAL OFFICE BLDG", "person": {"prefix": "Mr.", "name": "Shirley Roberts", "birthday": "1950-05-18", "gender": "male", "address": "Suite 682,21805 Schneider Mountains,Great Barrington,US", "phone": [{"system": "phone", "value": "1-648-179-0716", "use": "home"}], "languages": ["en-US"]}, "conds": [{"date": "1989-07-06", "type": "Cardiac Arrest", "status": "active"}, {"date": "1989-07-06", "type": "History of cardiac arrest (situation)", "status": "active"}, {"date": "1997-07-10", "type": "Myocardial Infarction", "status": "active"}, {"date": "1997-07-10", "type": "History of myocardial infarction (situation)", "status": "active"}], "immuns": [], "medreqs": [{"type": "Penicillin V Potassium 250 MG", "code": "834060", "date": "1964-11-26", "status": "active", "dosage": ""}], "observs": {"Cause of Death [US Standard Certificate of Death]": {"units": "N/A", "values": [{"date": "1997-07-10", "value": "Myocardial Infarction"}]}, "Quality adjusted life years": {"units": "years", "values": [{"date": "2017-10-31", "value": 47}]}, "Disability rating scale": {"units": "years", "values": [{"date": "2017-10-31", "value": 40.50138}]}}}