{"provider": "WINCHESTER HOSP COMM HEALTH INST", "person": {"prefix": "Mr.", "name": "Rosendo Hodkiewicz", "birthday": "1948-06-10", "gender": "male", "address": "61927 Rice Trace,Somerville,US", "phone": [{"system": "phone", "value": "761.444.9712", "use": "home"}], "languages": ["zh"]}, "conds": [{"date": "1967-07-25", "type": "Asthma", "status": "active"}, {"date": "2008-10-13", "type": "Osteoporosis (disorder)", "status": "active"}, {"date": "2012-05-24", "type": "Acute viral pharyngitis (disorder)", "status": "resolved"}, {"date": "2017-09-13", "type": "Injury of tendon of the rotator cuff of shoulder", "status": "active"}], "immuns": [{"date": "2008-10-13T22:55:43-04:00", "type": "Influenza, seasonal, injectable, preservative free"}, {"date": "2008-10-13T22:55:43-04:00", "type": "zoster"}, {"date": "2009-10-21T17:06:08-04:00", "type": "Influenza, seasonal, injectable, preservative free"}, {"date": "2009-10-21T17:06:08-04:00", "type": "Td (adult) preservative free"}, {"date": "2010-08-25T12:58:38-04:00", "type": "Influenza, seasonal, injectable, preservative free"}, {"date": "2011-09-10T19:58:17-04:00", "type": "Influenza, seasonal, injectable, preservative free"}, {"date": "2012-08-21T05:04:49-04:00", "type": "Influenza, seasonal, injectable, preservative free"}, {"date": "2013-09-09T02:53:48-04:00", "type": "Pneumococcal conjugate PCV 13"}, {"date": "2013-09-09T02:53:48-04:00", "type": "Influenza, seasonal, injectable, preservative free"}, {"date": "2014-10-20T13:03:19-04:00", "type": "Influenza, seasonal, injectable, preservative free"}, {"date": "2014-10-20T13:03:19-04:00", "type": "pneumococcal polysaccharide vaccine, 23 valent"}, {"date": "2015-10-18T16:53:10-04:00", "type": "Influenza, seasonal, injectable, preservative free"}, {"date": "2017-01-13T08:21:52-05:00", "type": "Influenza, seasonal, injectable, preservative free"}], "medreqs": [{"type": "Penicillin V Potassium 250 MG", "code": "834060", "date": "1950-07-19", "status": "active", "dosage": ""}, {"type": "120 ACTUAT Fluticasone propionate 0.044 MG/ACTUAT Metered Dose Inhaler", "code": "895994", "date": "1953-01-09", "status": "active", "dosage": {"sequence": 1, "asNeededBoolean": true}}, {"type": "200 ACTUAT Albuterol 0.09 MG/ACTUAT Metered Dose Inhaler", "code": "745679", "date": "1953-01-09", "status": "active", "dosage": {"sequence": 1, "asNeededBoolean": true}}, {"type": "Penicillin V Potassium 250 MG", "code": "834060", "date": "1955-03-16", "status": "active", "dosage": ""}, {"type": "Alendronic acid 10 MG [Fosamax]", "code": "904420", "date": "2008-10-13", "status": "active", "dosage": ""}], "observs": {"DXA [T-score] Bone density": {"units": "{T-score}", "values": [{"date": "2008-10-13", "value": -3.523104176345356}]}, "Body Height": {"units": "cm", "values": [{"date": "2008-10-13", "value": 181.34765554182414}, {"date": "2009-10-21", "value": 181.34765554182414}, {"date": "2010-08-25", "value": 181.34765554182414}, {"date": "2011-09-10", "value": 181.34765554182414}, {"date": "2012-08-21", "value": 181.34765554182414}, {"date": "2013-09-09", "value": 181.34765554182414}, {"date": "2014-10-20", "value": 181.34765554182414}, {"date": "2015-10-18", "value": 181.34765554182414}, {"date": "2017-01-13", "value": 181.34765554182414}]}, "Body Weight": {"units": "kg", "values": [{"date": "2008-10-13", "value": 133.38753818458702}, {"date": "2009-10-21", "value": 131.8086298223394}, {"date": "2010-08-25", "value": 130.20943844985425}, {"date": "2011-09-10", "value": 128.44891261823292}, {"date": "2012-08-21", "value": 127.36224626443816}, {"date": "2013-09-09", "value": 125.93256482797469}, {"date": "2014-10-20", "value": 124.0518290261681}, {"date": "2015-10-18", "value": 122.71500992687803}, {"date": "2017-01-13", "value": 121.59367940120484}]}, "Body Mass Index": {"units": "kg/m2", "values": [{"date": "2008-10-13", "value": 40.55938548948325}, {"date": "2009-10-21", "value": 40.07928402132099}, {"date": "2010-08-25", "value": 39.59301506223485}, {"date": "2011-09-10", "value": 39.05768884780162}, {"date": "2012-08-21", "value": 38.7272642808453}, {"date": "2013-09-09", "value": 38.29253850887374}, {"date": "2014-10-20", "value": 37.72065983544186}, {"date": "2015-10-18", "value": 37.31417087915887}, {"date": "2017-01-13", "value": 36.97320591593295}]}, "Systolic Blood Pressure": {"units": "mmHg", "values": [{"date": "2008-10-13", "value": 114}, {"date": "2009-10-21", "value": 118}, {"date": "2010-08-25", "value": 133}, {"date": "2011-09-10", "value": 109}, {"date": "2012-08-21", "value": 125}, {"date": "2013-09-09", "value": 120}, {"date": "2014-10-20", "value": 121}, {"date": "2015-10-18", "value": 118}, {"date": "2017-01-13", "value": 111}]}, "Diastolic Blood Pressure": {"units": "mmHg", "values": [{"date": "2008-10-13", "value": 77}, {"date": "2009-10-21", "value": 88}, {"date": "2010-08-25", "value": 79}, {"date": "2011-09-10", "value": 70}, {"date": "2012-08-21", "value": 73}, {"date": "2013-09-09", "value": 75}, {"date": "2014-10-20", "value": 78}, {"date": "2015-10-18", "value": 71}, {"date": "2017-01-13", "value": 87}]}, "Total Cholesterol": {"units": "mg/dL", "values": [{"date": "2008-10-13", "value": 199}, {"date": "2012-08-21", "value": 180}, {"date": "2015-10-18", "value": 172}]}, "Triglycerides": {"units": "mg/dL", "values": [{"date": "2008-10-13", "value": 135}, {"date": "2012-08-21", "value": 144}, {"date": "2015-10-18", "value": 123}]}, "Low Density Lipoprotein Cholesterol": {"units": "mg/dL", "values": [{"date": "2008-10-13", "value": 100}, {"date": "2012-08-21", "value": 73}, {"date": "2015-10-18", "value": 86}]}, "High Density Lipoprotein Cholesterol": {"units": "mg/dL", "values": [{"date": "2008-10-13", "value": 72}, {"date": "2012-08-21", "value": 78}, {"date": "2015-10-18", "value": 61}]}, "Oral temperature": {"units": "Cel", "values": [{"date": "2012-05-28", "value": 37}]}, "Quality adjusted life years": {"units": "years", "values": [{"date": "2017-10-31", "value": 67.50740977373923}]}, "Disability rating scale": {"units": "years", "values": [{"date": "2017-10-31", "value": 1.4925902262607806}]}}}