{"provider": "ST ANNE'S HOSPITAL PAIN MANAGMT CTR", "person": {"prefix": "Mr.", "name": "Arden Ankunding", "birthday": "1930-01-30", "gender": "male", "address": "521 Jayda Via,Rehoboth,US", "phone": [{"system": "phone", "value": "438.113.8588 x066", "use": "home"}], "languages": ["en-US"]}, "conds": [{"date": "1958-12-25", "type": "Cardiac Arrest", "status": "active"}, {"date": "1958-12-25", "type": "History of cardiac arrest (situation)", "status": "active"}, {"date": "1964-07-10", "type": "Prediabetes", "status": "active"}], "immuns": [], "medreqs": [], "observs": {"Cause of Death [US Standard Certificate of Death]": {"units": "N/A", "values": [{"date": "2005-08-18", "value": "Natural death with unknown cause"}]}, "Quality adjusted life years": {"units": "years", "values": [{"date": "2017-10-31", "value": 72.83827504758986}]}, "Disability rating scale": {"units": "years", "values": [{"date": "2017-10-31", "value": 19.494224952410157}]}}}