{"provider": "WINTHROP COMM HEALTH CENTER", "person": {"prefix": "", "name": "Abe Rogahn", "birthday": "2004-02-11", "gender": "male", "address": "6352 Herminia Square,Boston,US", "phone": [{"system": "phone", "value": "(253) 789-2744 x7159", "use": "home"}], "languages": ["en-US"]}, "conds": [{"date": "2011-11-20", "type": "Acute viral pharyngitis (disorder)", "status": "resolved"}, {"date": "2013-07-25", "type": "Viral sinusitis (disorder)", "status": "resolved"}, {"date": "2013-10-04", "type": "Injury of medial collateral ligament of knee", "status": "resolved"}, {"date": "2013-11-12", "type": "Viral sinusitis (disorder)", "status": "resolved"}, {"date": "2015-12-03", "type": "Laceration of thigh", "status": "resolved"}, {"date": "2017-08-13", "type": "Viral sinusitis (disorder)", "status": "resolved"}], "immuns": [{"date": "2008-03-03T11:44:12-05:00", "type": "DTaP"}, {"date": "2008-03-03T11:44:12-05:00", "type": "IPV"}, {"date": "2008-03-03T11:44:12-05:00", "type": "Influenza, seasonal, injectable, preservative free"}, {"date": "2008-03-03T11:44:12-05:00", "type": "MMR"}, {"date": "2008-03-03T11:44:12-05:00", "type": "varicella"}, {"date": "2009-02-21T23:29:33-05:00", "type": "Influenza, seasonal, injectable, preservative free"}, {"date": "2010-04-04T03:40:12-04:00", "type": "Influenza, seasonal, injectable, preservative free"}, {"date": "2011-06-01T05:50:05-04:00", "type": "Influenza, seasonal, injectable, preservative free"}, {"date": "2012-05-13T05:12:43-04:00", "type": "Influenza, seasonal, injectable, preservative free"}, {"date": "2013-05-16T09:24:20-04:00", "type": "Influenza, seasonal, injectable, preservative free"}, {"date": "2014-07-18T17:07:52-04:00", "type": "Influenza, seasonal, injectable, preservative free"}, {"date": "2015-07-06T06:01:36-04:00", "type": "Influenza, seasonal, injectable, preservative free"}, {"date": "2015-07-06T06:01:36-04:00", "type": "meningococcal MCV4P"}, {"date": "2015-07-06T06:01:36-04:00", "type": "Tdap"}, {"date": "2015-07-06T06:01:36-04:00", "type": "HPV, quadrivalent"}, {"date": "2016-07-23T04:32:34-04:00", "type": "Influenza, seasonal, injectable, preservative free"}, {"date": "2016-07-23T04:32:34-04:00", "type": "HPV, quadrivalent"}, {"date": "2017-05-17T02:33:10-04:00", "type": "Influenza, seasonal, injectable, preservative free"}, {"date": "2017-05-17T02:33:10-04:00", "type": "HPV, quadrivalent"}], "medreqs": [{"type": "Ibuprofen 100 MG Oral Tablet", "code": "198405", "date": "2013-10-11", "status": "stopped", "dosage": {"sequence": 1, "asNeededBoolean": true}}, {"type": "Acetaminophen 160 MG Oral Tablet", "code": "282464", "date": "2015-12-03", "status": "stopped", "dosage": {"sequence": 1, "asNeededBoolean": true}}, {"type": " Amoxicillin 250 MG / Clavulanate 125 MG [Augmentin]", "code": "824184", "date": "2017-08-19", "status": "stopped", "dosage": ""}], "observs": {"Body Height": {"units": "cm", "values": [{"date": "2008-03-03", "value": 100.66736914286761}, {"date": "2009-02-21", "value": 107.14470078109238}, {"date": "2010-04-04", "value": 113.9809470871657}, {"date": "2011-06-01", "value": 121.19759292246353}, {"date": "2012-05-13", "value": 127.03230817075955}, {"date": "2013-05-16", "value": 132.3279493078503}, {"date": "2014-07-18", "value": 137.91108359386743}, {"date": "2015-07-06", "value": 142.35470981093533}, {"date": "2016-07-23", "value": 148.7643992678294}, {"date": "2017-05-17", "value": 154.9117135175041}]}, "Body Weight": {"units": "kg", "values": [{"date": "2008-03-03", "value": 15.846516383102406}, {"date": "2009-02-21", "value": 17.91115193813805}, {"date": "2010-04-04", "value": 20.27305726608721}, {"date": "2011-06-01", "value": 22.947073551288458}, {"date": "2012-05-13", "value": 25.4572158621132}, {"date": "2013-05-16", "value": 28.304767070984948}, {"date": "2014-07-18", "value": 32.21440712970154}, {"date": "2015-07-06", "value": 35.829661626023906}, {"date": "2016-07-23", "value": 40.76133536533477}, {"date": "2017-05-17", "value": 44.96505096853625}]}, "Body Mass Index": {"units": "kg/m2", "values": [{"date": "2008-03-03", "value": 15.637105501331027}, {"date": "2009-02-21", "value": 15.602066522919122}, {"date": "2010-04-04", "value": 15.604674877231467}, {"date": "2011-06-01", "value": 15.622096590099444}, {"date": "2012-05-13", "value": 15.77547797371281}, {"date": "2013-05-16", "value": 16.16428208431758}, {"date": "2014-07-18", "value": 16.93759723493066}, {"date": "2015-07-06", "value": 17.680682523897406}, {"date": "2016-07-23", "value": 18.418335414617143}, {"date": "2017-05-17", "value": 18.73728119536039}]}, "Systolic Blood Pressure": {"units": "mmHg", "values": [{"date": "2008-03-03", "value": 127}, {"date": "2009-02-21", "value": 136}, {"date": "2010-04-04", "value": 122}, {"date": "2011-06-01", "value": 129}, {"date": "2012-05-13", "value": 112}, {"date": "2013-05-16", "value": 103}, {"date": "2014-07-18", "value": 119}, {"date": "2015-07-06", "value": 100}, {"date": "2016-07-23", "value": 105}, {"date": "2017-05-17", "value": 116}]}, "Diastolic Blood Pressure": {"units": "mmHg", "values": [{"date": "2008-03-03", "value": 88}, {"date": "2009-02-21", "value": 77}, {"date": "2010-04-04", "value": 80}, {"date": "2011-06-01", "value": 83}, {"date": "2012-05-13", "value": 73}, {"date": "2013-05-16", "value": 72}, {"date": "2014-07-18", "value": 85}, {"date": "2015-07-06", "value": 78}, {"date": "2016-07-23", "value": 84}, {"date": "2017-05-17", "value": 75}]}, "Oral temperature": {"units": "Cel", "values": [{"date": "2011-11-20", "value": 37}]}, "Quality adjusted life years": {"units": "years", "values": [{"date": "2017-10-31", "value": 12.994264995072099}]}, "Disability rating scale": {"units": "years", "values": [{"date": "2017-10-31", "value": 0.005735004927900484}]}}}