{"provider": "WINTHROP COMM HEALTH CENTER", "person": {"prefix": "Mrs.", "name": "Elin Osinski", "birthday": "1929-10-20", "gender": "female", "address": "Suite 564,2104 Iliana Junctions,Boston,US", "phone": [{"system": "phone", "value": "1-328-193-1430 x456", "use": "home"}], "languages": ["en-US"]}, "conds": [{"date": "1943-10-20", "type": "Chronic sinusitis (disorder)", "status": "active"}, {"date": "1948-09-05", "type": "Hypertension", "status": "active"}, {"date": "1949-09-10", "type": "Asthma", "status": "active"}], "immuns": [], "medreqs": [{"type": "120 ACTUAT Fluticasone propionate 0.044 MG/ACTUAT Metered Dose Inhaler", "code": "895994", "date": "1932-02-08", "status": "active", "dosage": {"sequence": 1, "asNeededBoolean": true}}, {"type": "200 ACTUAT Albuterol 0.09 MG/ACTUAT Metered Dose Inhaler", "code": "745679", "date": "1932-02-08", "status": "active", "dosage": {"sequence": 1, "asNeededBoolean": true}}, {"type": "Penicillin V Potassium 250 MG", "code": "834060", "date": "1946-10-14", "status": "active", "dosage": ""}], "observs": {"Cause of Death [US Standard Certificate of Death]": {"units": "N/A", "values": [{"date": "1964-12-20", "value": "Natural death with unknown cause"}]}, "Quality adjusted life years": {"units": "years", "values": [{"date": "2017-10-31", "value": 34.22624682626237}]}, "Disability rating scale": {"units": "years", "values": [{"date": "2017-10-31", "value": 53.13425317373763}]}}}