{"provider": "CLARK CENTER CAPE COD HEALTHCARE CA", "person": {"prefix": "Mr.", "name": "Huey Pfannerstill", "birthday": "1923-09-21", "gender": "male", "address": "Suite 112,93113 Eva Branch,Falmouth,US", "phone": [{"system": "phone", "value": "(590) 948-4525", "use": "home"}], "languages": ["en-US"]}, "conds": [{"date": "1973-11-17", "type": "Prediabetes", "status": "active"}, {"date": "2002-08-22", "type": "Alzheimer's disease (disorder)", "status": "active"}, {"date": "2013-10-18", "type": "Stroke", "status": "active"}, {"date": "2013-11-10", "type": "Viral sinusitis (disorder)", "status": "resolved"}, {"date": "2013-12-25", "type": "Coronary Heart Disease", "status": "active"}, {"date": "2013-12-25", "type": "Osteoporosis (disorder)", "status": "active"}, {"date": "2017-04-26", "type": "Pneumonia", "status": "active"}], "immuns": [{"date": "2008-10-02T06:17:21-04:00", "type": "Influenza, seasonal, injectable, preservative free"}, {"date": "2009-10-24T21:20:42-04:00", "type": "Influenza, seasonal, injectable, preservative free"}, {"date": "2010-10-16T02:04:32-04:00", "type": "Influenza, seasonal, injectable, preservative free"}, {"date": "2011-12-02T23:01:30-05:00", "type": "Influenza, seasonal, injectable, preservative free"}, {"date": "2012-10-28T19:35:14-04:00", "type": "Influenza, seasonal, injectable, preservative free"}, {"date": "2013-12-25T01:47:17-05:00", "type": "Influenza, seasonal, injectable, preservative free"}, {"date": "2015-01-04T21:22:31-05:00", "type": "Influenza, seasonal, injectable, preservative free"}, {"date": "2015-01-04T21:22:31-05:00", "type": "Td (adult) preservative free"}, {"date": "2016-03-17T06:22:46-04:00", "type": "Influenza, seasonal, injectable, preservative free"}, {"date": "2017-03-12T18:28:01-04:00", "type": "Influenza, seasonal, injectable, preservative free"}], "medreqs": [{"type": "Penicillin V Potassium 250 MG", "code": "834060", "date": "1937-02-28", "status": "active", "dosage": ""}, {"type": "Penicillin V Potassium 250 MG", "code": "834060", "date": "1940-11-16", "status": "active", "dosage": ""}, {"type": "Penicillin V Potassium 500 MG", "code": "834101", "date": "1948-02-12", "status": "active", "dosage": ""}, {"type": "Galantamine 4 MG [Razadyne]", "code": "602735", "date": "2002-08-22", "status": "active", "dosage": ""}, {"type": "Memantine hydrochloride 2 MG/ML [Namenda]", "code": "996741", "date": "2004-03-05", "status": "active", "dosage": ""}, {"type": "Clopidogrel 75 MG Oral Tablet", "code": "309362", "date": "2013-10-18", "status": "stopped", "dosage": ""}, {"type": "Alteplase 1 MG/ML Injectable Solution", "code": "308056", "date": "2013-10-18", "status": "stopped", "dosage": ""}, {"type": "Clopidogrel 75 MG Oral Tablet", "code": "309362", "date": "2013-12-25", "status": "active", "dosage": ""}, {"type": "Simvastatin 20 MG Oral Tablet", "code": "312961", "date": "2013-12-25", "status": "active", "dosage": ""}, {"type": "Amlodipine 5 MG Oral Tablet", "code": "197361", "date": "2013-12-25", "status": "active", "dosage": ""}, {"type": "Nitroglycerin 0.4 MG/ACTUAT [Nitrolingual]", "code": "564666", "date": "2013-12-25", "status": "active", "dosage": ""}, {"type": "Alendronic acid 10 MG [Fosamax]", "code": "904420", "date": "2013-12-25", "status": "active", "dosage": ""}], "observs": {"Total score [MMSE]": {"units": "(score)", "values": [{"date": "2008-02-06", "value": 4}]}, "Hemoglobin A1c/Hemoglobin.total in Blood": {"units": "%", "values": [{"date": "2008-10-02", "value": 6.1}, {"date": "2008-10-02", "value": 6.1}, {"date": "2009-10-24", "value": 5.9}, {"date": "2009-10-24", "value": 5.9}, {"date": "2010-10-16", "value": 6.0}, {"date": "2010-10-16", "value": 6.0}, {"date": "2011-12-02", "value": 6.2}, {"date": "2011-12-02", "value": 6.2}, {"date": "2012-10-28", "value": 6.1}, {"date": "2012-10-28", "value": 6.1}, {"date": "2013-12-25", "value": 5.9}, {"date": "2013-12-25", "value": 5.9}, {"date": "2015-01-04", "value": 6.2}, {"date": "2015-01-04", "value": 6.2}, {"date": "2016-03-17", "value": 5.8}, {"date": "2016-03-17", "value": 5.8}, {"date": "2017-03-12", "value": 6.3}, {"date": "2017-03-12", "value": 6.3}]}, "Body Height": {"units": "cm", "values": [{"date": "2008-10-02", "value": 174.40647329543813}, {"date": "2009-10-24", "value": 174.40647329543813}, {"date": "2010-10-16", "value": 174.40647329543813}, {"date": "2011-12-02", "value": 174.40647329543813}, {"date": "2012-10-28", "value": 174.40647329543813}, {"date": "2013-12-25", "value": 174.40647329543813}, {"date": "2015-01-04", "value": 174.40647329543813}, {"date": "2016-03-17", "value": 174.40647329543813}, {"date": "2017-03-12", "value": 174.40647329543813}]}, "Body Weight": {"units": "kg", "values": [{"date": "2008-10-02", "value": 60.27310525052777}, {"date": "2009-10-24", "value": 58.389691657693724}, {"date": "2010-10-16", "value": 56.935550541835724}, {"date": "2011-12-02", "value": 55.61228056740689}, {"date": "2012-10-28", "value": 54.204032604581826}, {"date": "2013-12-25", "value": 52.89685530912404}, {"date": "2015-01-04", "value": 51.665249703237976}, {"date": "2016-03-17", "value": 49.787355252547}, {"date": "2017-03-12", "value": 47.960412394813545}]}, "Body Mass Index": {"units": "kg/m2", "values": [{"date": "2008-10-02", "value": 19.81519571798175}, {"date": "2009-10-24", "value": 19.19601061370032}, {"date": "2010-10-16", "value": 18.71795177315239}, {"date": "2011-12-02", "value": 18.282917715722498}, {"date": "2012-10-28", "value": 17.819946563218565}, {"date": "2013-12-25", "value": 17.390203084100715}, {"date": "2015-01-04", "value": 16.98530431496384}, {"date": "2016-03-17", "value": 16.367933666421926}, {"date": "2017-03-12", "value": 15.767313702657237}]}, "Systolic Blood Pressure": {"units": "mmHg", "values": [{"date": "2008-10-02", "value": 120}, {"date": "2009-10-24", "value": 122}, {"date": "2010-10-16", "value": 139}, {"date": "2011-12-02", "value": 137}, {"date": "2012-10-28", "value": 134}, {"date": "2013-12-25", "value": 136}, {"date": "2015-01-04", "value": 136}, {"date": "2016-03-17", "value": 132}, {"date": "2017-03-12", "value": 136}]}, "Diastolic Blood Pressure": {"units": "mmHg", "values": [{"date": "2008-10-02", "value": 89}, {"date": "2009-10-24", "value": 75}, {"date": "2010-10-16", "value": 75}, {"date": "2011-12-02", "value": 79}, {"date": "2012-10-28", "value": 88}, {"date": "2013-12-25", "value": 76}, {"date": "2015-01-04", "value": 71}, {"date": "2016-03-17", "value": 87}, {"date": "2017-03-12", "value": 83}]}, "Glucose": {"units": "mg/dL", "values": [{"date": "2008-10-02", "value": 85}, {"date": "2009-10-24", "value": 98}, {"date": "2010-10-16", "value": 65}, {"date": "2011-12-02", "value": 70}, {"date": "2012-10-28", "value": 77}, {"date": "2013-12-25", "value": 95}, {"date": "2015-01-04", "value": 70}, {"date": "2016-03-17", "value": 79}, {"date": "2017-03-12", "value": 100}]}, "Urea Nitrogen": {"units": "mg/dL", "values": [{"date": "2008-10-02", "value": 8}, {"date": "2009-10-24", "value": 10}, {"date": "2010-10-16", "value": 15}, {"date": "2011-12-02", "value": 7}, {"date": "2012-10-28", "value": 20}, {"date": "2013-12-25", "value": 17}, {"date": "2015-01-04", "value": 20}, {"date": "2016-03-17", "value": 14}, {"date": "2017-03-12", "value": 12}]}, "Creatinine": {"units": "mg/dL", "values": [{"date": "2008-10-02", "value": 1.0}, {"date": "2009-10-24", "value": 1.0}, {"date": "2010-10-16", "value": 1.0}, {"date": "2011-12-02", "value": 1.0}, {"date": "2012-10-28", "value": 1.0}, {"date": "2013-12-25", "value": 1.0}, {"date": "2015-01-04", "value": 1.0}, {"date": "2016-03-17", "value": 1.0}, {"date": "2017-03-12", "value": 1.0}]}, "Calcium": {"units": "mg/dL", "values": [{"date": "2008-10-02", "value": 9.570906338708689}, {"date": "2009-10-24", "value": 8.859007932048915}, {"date": "2010-10-16", "value": 9.465067556559244}, {"date": "2011-12-02", "value": 9.556147426920173}, {"date": "2012-10-28", "value": 9.65565074808607}, {"date": "2013-12-25", "value": 9.527606424363963}, {"date": "2015-01-04", "value": 8.524574728969402}, {"date": "2016-03-17", "value": 8.994534948202551}, {"date": "2017-03-12", "value": 8.600315002823525}]}, "Sodium": {"units": "mmol/L", "values": [{"date": "2008-10-02", "value": 141}, {"date": "2009-10-24", "value": 141}, {"date": "2010-10-16", "value": 142}, {"date": "2011-12-02", "value": 138}, {"date": "2012-10-28", "value": 143}, {"date": "2013-12-25", "value": 144}, {"date": "2015-01-04", "value": 142}, {"date": "2016-03-17", "value": 139}, {"date": "2017-03-12", "value": 138}]}, "Potassium": {"units": "mmol/L", "values": [{"date": "2008-10-02", "value": 4.532269191155419}, {"date": "2009-10-24", "value": 4.739723659641209}, {"date": "2010-10-16", "value": 3.727858300882608}, {"date": "2011-12-02", "value": 3.8676175133690327}, {"date": "2012-10-28", "value": 4.153445332561646}, {"date": "2013-12-25", "value": 4.156627462559063}, {"date": "2015-01-04", "value": 4.233164198324547}, {"date": "2016-03-17", "value": 4.884636993445104}, {"date": "2017-03-12", "value": 4.033452705630495}]}, "Chloride": {"units": "mmol/L", "values": [{"date": "2008-10-02", "value": 105}, {"date": "2009-10-24", "value": 106}, {"date": "2010-10-16", "value": 108}, {"date": "2011-12-02", "value": 106}, {"date": "2012-10-28", "value": 111}, {"date": "2013-12-25", "value": 103}, {"date": "2015-01-04", "value": 108}, {"date": "2016-03-17", "value": 105}, {"date": "2017-03-12", "value": 111}]}, "Carbon Dioxide": {"units": "mmol/L", "values": [{"date": "2008-10-02", "value": 26}, {"date": "2009-10-24", "value": 28}, {"date": "2010-10-16", "value": 26}, {"date": "2011-12-02", "value": 27}, {"date": "2012-10-28", "value": 26}, {"date": "2013-12-25", "value": 28}, {"date": "2015-01-04", "value": 23}, {"date": "2016-03-17", "value": 25}, {"date": "2017-03-12", "value": 23}]}, "Total Cholesterol": {"units": "mg/dL", "values": [{"date": "2011-12-02", "value": 166}, {"date": "2015-01-04", "value": 182}]}, "Triglycerides": {"units": "mg/dL", "values": [{"date": "2011-12-02", "value": 113}, {"date": "2015-01-04", "value": 125}]}, "Low Density Lipoprotein Cholesterol": {"units": "mg/dL", "values": [{"date": "2011-12-02", "value": 77}, {"date": "2015-01-04", "value": 88}]}, "High Density Lipoprotein Cholesterol": {"units": "mg/dL", "values": [{"date": "2011-12-02", "value": 66}, {"date": "2015-01-04", "value": 69}]}, "DXA [T-score] Bone density": {"units": "{T-score}", "values": [{"date": "2013-12-25", "value": -3.150736692023925}]}, "Cause of Death [US Standard Certificate of Death]": {"units": "N/A", "values": [{"date": "2017-05-09", "value": "Pneumonia"}]}, "Quality adjusted life years": {"units": "years", "values": [{"date": "2017-10-31", "value": 89.06511293450056}]}, "Disability rating scale": {"units": "years", "values": [{"date": "2017-10-31", "value": 12.583107065499455}]}}}