{"provider": "BERKSHIRE MED CTR INC/HILLCREST CAM", "person": {"prefix": "Ms.", "name": "Cassi Strosin", "birthday": "1987-04-09", "gender": "female", "address": "Apt. 590,1246 Abshire Locks,Pittsfield,US", "phone": [{"system": "phone", "value": "182.878.8918 x8651", "use": "home"}], "languages": ["en-US"]}, "conds": [{"date": "2008-11-06", "type": "Normal pregnancy", "status": "resolved"}, {"date": "2012-08-27", "type": "Rupture of patellar tendon", "status": "resolved"}, {"date": "2015-07-16", "type": "Normal pregnancy", "status": "resolved"}], "immuns": [{"date": "2008-03-27T11:15:21-04:00", "type": "Influenza, seasonal, injectable, preservative free"}, {"date": "2011-03-16T02:57:50-04:00", "type": "Influenza, seasonal, injectable, preservative free"}, {"date": "2011-03-16T02:57:50-04:00", "type": "Td (adult) preservative free"}, {"date": "2014-08-12T12:33:11-04:00", "type": "Influenza, seasonal, injectable, preservative free"}, {"date": "2017-07-13T21:40:45-04:00", "type": "Influenza, seasonal, injectable, preservative free"}], "medreqs": [{"type": "NuvaRing 0.12/0.015 MG per 24HR 21 Day Vaginal Ring", "code": "1367439", "date": "2007-04-16", "status": "stopped", "dosage": ""}, {"type": "Seasonique 91 Day Pack", "code": "749762", "date": "2009-05-28", "status": "stopped", "dosage": ""}, {"type": "Yaz 28 Day Pack", "code": "748856", "date": "2010-05-28", "status": "stopped", "dosage": ""}, {"type": "Seasonique 91 Day Pack", "code": "749762", "date": "2011-05-28", "status": "stopped", "dosage": ""}, {"type": "Acetaminophen 325 MG / HYDROcodone Bitartrate 7.5 MG Oral Tablet", "code": "857005", "date": "2012-09-03", "status": "stopped", "dosage": {"sequence": 1, "timing": {"repeat": {"frequency": 1, "period": 6, "periodUnit": "h"}}, "asNeededBoolean": false, "doseQuantity": {"value": 1}}}, {"type": "Naproxen sodium 220 MG Oral Tablet", "code": "849574", "date": "2012-09-03", "status": "stopped", "dosage": {"sequence": 1, "asNeededBoolean": true}}, {"type": "Natazia 28 Day Pack", "code": "978950", "date": "2016-05-28", "status": "stopped", "dosage": ""}], "observs": {"Body Height": {"units": "cm", "values": [{"date": "2008-03-27", "value": 171.73439847526558}, {"date": "2011-03-16", "value": 171.73439847526558}, {"date": "2014-08-12", "value": 171.73439847526558}, {"date": "2017-07-13", "value": 171.73439847526558}]}, "Body Weight": {"units": "kg", "values": [{"date": "2008-03-27", "value": 57.03016777459647}, {"date": "2011-03-16", "value": 61.24020205225287}, {"date": "2014-08-12", "value": 67.67514892252606}, {"date": "2017-07-13", "value": 72.38070529885242}]}, "Body Mass Index": {"units": "kg/m2", "values": [{"date": "2008-03-27", "value": 19.337042988685965}, {"date": "2011-03-16", "value": 20.76452631878317}, {"date": "2014-08-12", "value": 22.946403895440245}, {"date": "2017-07-13", "value": 24.54190237432144}]}, "Systolic Blood Pressure": {"units": "mmHg", "values": [{"date": "2008-03-27", "value": 100}, {"date": "2011-03-16", "value": 115}, {"date": "2014-08-12", "value": 110}, {"date": "2017-07-13", "value": 128}]}, "Diastolic Blood Pressure": {"units": "mmHg", "values": [{"date": "2008-03-27", "value": 82}, {"date": "2011-03-16", "value": 84}, {"date": "2014-08-12", "value": 82}, {"date": "2017-07-13", "value": 88}]}, "Total Cholesterol": {"units": "mg/dL", "values": [{"date": "2017-07-13", "value": 176}]}, "Triglycerides": {"units": "mg/dL", "values": [{"date": "2017-07-13", "value": 103}]}, "Low Density Lipoprotein Cholesterol": {"units": "mg/dL", "values": [{"date": "2017-07-13", "value": 83}]}, "High Density Lipoprotein Cholesterol": {"units": "mg/dL", "values": [{"date": "2017-07-13", "value": 72}]}, "Quality adjusted life years": {"units": "years", "values": [{"date": "2017-10-31", "value": 29.982763423772923}]}, "Disability rating scale": {"units": "years", "values": [{"date": "2017-10-31", "value": 0.0172365762270763}]}}}